{
  "ComponentType": {
    "PROMPT": 1,
    "YYYYMM": 2,
    "YYYY": 3,
    "YY": 4,
    "YYMM": 5,
    "SEQUENCE_MONTH": 6,
    "SEQUENCE_YEAR": 7,
    "SEQUENCE_RUNNING": 8,
    "INITIAL_UNIT": 9,
    "OWNER_UNIT": 10
  },
  "lookup_types": {
    "CODELIST": "code-list",
    "NFLIST": "nf-list"
  },
  "MeddraLevel": {
    "LLT": "LLT",
    "PT": "PT",
    "HLGT": "HLGT",
    "HLT": "HLT",
    "SOC": "SOC"
  },
  "MeddraCondition": {
    "STARTSWITH": "startswith",
    "EXACT": "exact",
    "CONTAINS": "contains"
  },
  "MeddraOrderBy": {
    "CODE": "Code",
    "TERM": "Term"
  },
  "MeddraSoctype": {
    "Y": "Y",
    "N": "N"
  }
}
